django_unfurl-0.1.1.dist-info/DESCRIPTION.rst
django_unfurl-0.1.1.dist-info/LICENSE.txt
django_unfurl-0.1.1.dist-info/METADATA
django_unfurl-0.1.1.dist-info/RECORD
django_unfurl-0.1.1.dist-info/WHEEL
django_unfurl-0.1.1.dist-info/metadata.json
django_unfurl-0.1.1.dist-info/top_level.txt
unfurl/__init__.py
unfurl/apps.py
unfurl/extractor.py
unfurl/urls.py
unfurl/views.py
unfurl/management/__init__.py
unfurl/management/commands/__init__.py
unfurl/management/commands/urls_list.py
unfurl/templates/unfurl/base.html
unfurl/templates/unfurl/urls_list.html
unfurl/templates/unfurl/urls_list_item.html
unfurl/tests/__init__.py
unfurl/tests/test_views.py
