Metadata-Version: 2.0
Name: django-unfurl
Version: 0.1.1
Summary: A small re-usable app for Django to output all the URLs used in a project
Home-page: https://github.com/kezabelle/django-unfurl
Author: Keryn Knight
Author-email: django-unfurl@kerynknight.com
License: BSD License
Keywords: django unfurl urls urlconf
Platform: UNKNOWN
Classifier: Development Status :: 3 - Alpha
Classifier: Intended Audience :: Developers
Classifier: License :: OSI Approved :: BSD License
Classifier: Natural Language :: English
Classifier: Programming Language :: Python :: 2
Classifier: Programming Language :: Python :: 2.7
Classifier: Programming Language :: Python :: 3
Classifier: Programming Language :: Python :: 3.3
Classifier: Programming Language :: Python :: 3.4
Classifier: Programming Language :: Python :: 3.5
Classifier: Framework :: Django
Classifier: Framework :: Django :: 1.10
Classifier: Framework :: Django :: 1.8
Classifier: Framework :: Django :: 1.9
Requires-Dist: Django (>=1.8)
